MANIFEST.in
README.rst
setup.py
rawdata/__init__.py
rawdata/config.py
rawdata/content.py
rawdata/errors.py
rawdata/events.py
rawdata/gather.py
rawdata/generate.py
rawdata.egg-info/PKG-INFO
rawdata.egg-info/SOURCES.txt
rawdata.egg-info/dependency_links.txt
rawdata.egg-info/requires.txt
rawdata.egg-info/top_level.txt
rawdata/data/_index.ndx
rawdata/data/contacts.csv
rawdata/data/countries.csv
rawdata/data/diary.csv
rawdata/data/finance_categories.txt
rawdata/data/names.csv
rawdata/data/notes.csv
rawdata/data/nouns.txt
rawdata/data/sample.csv
rawdata/data/tasks.csv
rawdata/data/finance/mining_copper_rent.csv
rawdata/data/food/combinations.csv
rawdata/data/food/food_desc.cit
rawdata/data/food/food_desc.csv
rawdata/data/food/food_groups.csv
rawdata/data/food/garden_produce.csv
rawdata/data/games/classes.csv
rawdata/data/games/materials.csv
rawdata/data/games/monsters.csv
rawdata/data/games/races.csv
rawdata/data/games/skills.csv
rawdata/data/games/stats.csv
rawdata/data/pim/file_types.csv
rawdata/data/pim/pim_types.csv